CONTRIBUTING.md
MANIFEST.in
README.rst
setup.py
docs/HISTORY.txt
docs/LICENSE.GPL
docs/LICENSE.txt
eea/__init__.py
eea.depiction.egg-info/PKG-INFO
eea.depiction.egg-info/SOURCES.txt
eea.depiction.egg-info/dependency_links.txt
eea.depiction.egg-info/entry_points.txt
eea.depiction.egg-info/namespace_packages.txt
eea.depiction.egg-info/not-zip-safe
eea.depiction.egg-info/requires.txt
eea.depiction.egg-info/top_level.txt
eea/depiction/README.txt
eea/depiction/__init__.py
eea/depiction/adapters.py
eea/depiction/config.py
eea/depiction/configure.zcml
eea/depiction/interfaces.py
eea/depiction/marshaller.py
eea/depiction/marshaller.txt
eea/depiction/overrides.zcml
eea/depiction/profiles.zcml
eea/depiction/setuphandlers.py
eea/depiction/skins.zcml
eea/depiction/traverse.py
eea/depiction/version.txt
eea/depiction/async/__init__.py
eea/depiction/async/configure.zcml
eea/depiction/async/subscribers.py
eea/depiction/browser/__init__.py
eea/depiction/browser/atfield.py
eea/depiction/browser/atfield.txt
eea/depiction/browser/atfield.zcml
eea/depiction/browser/atfolder.py
eea/depiction/browser/atfolder.txt
eea/depiction/browser/atfolder.zcml
eea/depiction/browser/attopic.txt
eea/depiction/browser/attopic.zcml
eea/depiction/browser/configure.zcml
eea/depiction/browser/default.py
eea/depiction/browser/dexterity.py
eea/depiction/browser/dexterity.zcml
eea/depiction/browser/interfaces.py
eea/depiction/browser/multimedia.py
eea/depiction/browser/multimedia.txt
eea/depiction/browser/multimedia.zcml
eea/depiction/browser/recreate_scales.pt
eea/depiction/browser/scales.py
eea/depiction/browser/thumbnail_view.pt
eea/depiction/browser/images/generic.jpg
eea/depiction/browser/images/play-button.png
eea/depiction/cache/__init__.py
eea/depiction/cache/nocache.py
eea/depiction/content/__init__.py
eea/depiction/content/configure.zcml
eea/depiction/content/interfaces.py
eea/depiction/content/tool.gif
eea/depiction/content/tool.py
eea/depiction/profiles/default/componentregistry.xml
eea/depiction/profiles/default/controlpanel.xml
eea/depiction/profiles/default/eea.depiction.txt
eea/depiction/profiles/default/metadata.xml
eea/depiction/profiles/default/propertiestool.xml
eea/depiction/profiles/default/skins.xml
eea/depiction/profiles/default/toolset.xml
eea/depiction/profiles/default/types.xml
